onlymaps/__init__.py
onlymaps/__init__.pyi
onlymaps/_connection.py
onlymaps/_drivers.py
onlymaps/_params.py
onlymaps/_pool.py
onlymaps/_query.py
onlymaps/_spec.py
onlymaps/_types.py
onlymaps/_utils.py
onlymaps/_version.py
onlymaps/asyncio/__init__.py
onlymaps/asyncio/__init__.pyi
onlymaps/asyncio/_connection.py
onlymaps/asyncio/_pool.py
onlymaps/asyncio/_query.py
onlymaps/asyncio/_spec.py
onlymaps-0.2.0.dist-info/licenses/LICENSE
onlymaps-0.2.0.dist-info/METADATA
onlymaps-0.2.0.dist-info/WHEEL
onlymaps-0.2.0.dist-info/top_level.txt
onlymaps-0.2.0.dist-info/RECORD
