Metadata-Version: 2.4
Name: onlymaps
Version: 0.2.0
Summary: A Python micro-ORM
Author: Manos Stoumpos
Author-email: manosstoumpos@gmail.com
License: MIT
Project-URL: Homepage, https://github.com/manoss96/onlymaps
Project-URL: Bug Tracker, https://github.com/manoss96/onlymaps/issues
Project-URL: Documentation, https://onlymaps.rtfd.io
Project-URL: Changelog, https://github.com/manoss96/onlymaps/blob/main/CHANGELOG.md
Keywords: python,orm,sql,postgresql,mysql
Classifier: Programming Language :: Python :: 3
Classifier: License :: OSI Approved :: MIT License
Classifier: Operating System :: OS Independent
Requires-Python: >=3.11
License-File: LICENSE
Requires-Dist: pydantic==2.12.3
Provides-Extra: psycopg
Requires-Dist: psycopg[binary]==3.2.10; extra == "psycopg"
Provides-Extra: pymysql
Requires-Dist: pymysql==1.1.2; extra == "pymysql"
Requires-Dist: types-PyMySQL==1.1.0.20250916; extra == "pymysql"
Provides-Extra: mariadb
Requires-Dist: mariadb==1.1.14; extra == "mariadb"
Provides-Extra: pymssql
Requires-Dist: pymssql==2.3.8; extra == "pymssql"
Provides-Extra: oracledb
Requires-Dist: oracledb==3.4.1; extra == "oracledb"
Provides-Extra: duckdb
Requires-Dist: duckdb==1.4.3; extra == "duckdb"
Provides-Extra: aiomysql
Requires-Dist: aiomysql==0.3.2; extra == "aiomysql"
Provides-Extra: aiosqlite
Requires-Dist: aiosqlite==0.21.0; extra == "aiosqlite"
Provides-Extra: all
Requires-Dist: psycopg[binary]==3.2.10; extra == "all"
Requires-Dist: pymysql==1.1.2; extra == "all"
Requires-Dist: types-PyMySQL==1.1.0.20250916; extra == "all"
Requires-Dist: mariadb==1.1.14; extra == "all"
Requires-Dist: pymssql==2.3.8; extra == "all"
Requires-Dist: oracledb==3.4.1; extra == "all"
Requires-Dist: duckdb==1.4.3; extra == "all"
Requires-Dist: aiomysql==0.3.2; extra == "all"
Requires-Dist: aiosqlite==0.21.0; extra == "all"
Provides-Extra: dev
Requires-Dist: pytest==9.0.1; extra == "dev"
Requires-Dist: pytest-asyncio==1.3.0; extra == "dev"
Requires-Dist: testcontainers[mssql,mysql,oracle-free,postgres]==4.13.2; extra == "dev"
Requires-Dist: coverage==7.2.1; extra == "dev"
Requires-Dist: mypy==1.18.2; extra == "dev"
Requires-Dist: pylint==3.3.1; extra == "dev"
Requires-Dist: pylint-pydantic==0.3.2; extra == "dev"
Requires-Dist: black==24.10.0; extra == "dev"
Requires-Dist: isort==5.13.2; extra == "dev"
Requires-Dist: invoke==2.2.1; extra == "dev"
Dynamic: license-file
